bondable/__init__.py
bondable/app/__init__.py
bondable/app/auth.py
bondable/app/chat_page.py
bondable/app/index.py
bondable/app/start.py
bondable/app/threads_page.py
bondable/bond/__init__.py
bondable/bond/agent.py
bondable/bond/auth.py
bondable/bond/broker.py
bondable/bond/builder.py
bondable/bond/cache.py
bondable/bond/config.py
bondable/bond/decorator.py
bondable/bond/functions.py
bondable/bond/metadata.py
bondable/bond/page.py
bondable/bond/pages.py
bondable/bond/threads.py
bondable/management/__init__.py
bondable/management/delete_threads.py
bondable/management/show_threads.py
bondable-0.1.15.dist-info/METADATA
bondable-0.1.15.dist-info/WHEEL
bondable-0.1.15.dist-info/RECORD
