Metadata-Version: 2.3
Name: bondable
Version: 0.1.15
Summary: Bond AI is and SDK and UI for working with agents built using the OpenAI Assistants API
License: MIT
Author: jmcarnahan
Author-email: jmcarny@gmail.com
Requires-Python: >=3.12,<3.13
Classifier: License :: OSI Approved :: MIT License
Classifier: Programming Language :: Python :: 3
Classifier: Programming Language :: Python :: 3.12
Requires-Dist: google-api-python-client (>=2.163.0,<3.0.0)
Requires-Dist: google-auth (>=2.38.0,<3.0.0)
Requires-Dist: google-auth-httplib2 (>=0.2.0,<0.3.0)
Requires-Dist: google-auth-oauthlib (>=1.2.1,<2.0.0)
Requires-Dist: google-cloud-secret-manager (>=2.23.1,<3.0.0)
Requires-Dist: ipython (>=8.31.0,<9.0.0)
Requires-Dist: openai (>=1.66.3,<2.0.0)
Requires-Dist: poetry-plugin-export (>=1.9.0,<2.0.0)
Requires-Dist: pytest (>=8.3.4,<9.0.0)
Requires-Dist: python-dotenv (>=1.0.1,<2.0.0)
Requires-Dist: sqlalchemy (>=2.0.36,<3.0.0)
Requires-Dist: streamlit-cookies-controller (>=0.0.4,<0.0.5)
Project-URL: Homepage, https://github.com/jmcarnahan/bond-ai
Project-URL: Repository, https://github.com/jmcarnahan/bond-ai
